nagios_unity-0.1.2.dist-info/DESCRIPTION.rst
nagios_unity-0.1.2.dist-info/METADATA
nagios_unity-0.1.2.dist-info/RECORD
nagios_unity-0.1.2.dist-info/WHEEL
nagios_unity-0.1.2.dist-info/entry_points.txt
nagios_unity-0.1.2.dist-info/metadata.json
nagios_unity-0.1.2.dist-info/top_level.txt
nagiosunity/__init__.py
nagiosunity/cli/__init__.py
nagiosunity/cli/client.py
nagiosunity/cli/opt.py
nagiosunity/commands/__init__.py
nagiosunity/commands/array_hardware.py
nagiosunity/commands/battery.py
nagiosunity/commands/dae.py
nagiosunity/commands/disk.py
nagiosunity/commands/dpe.py
nagiosunity/commands/ethernet_port.py
nagiosunity/commands/fan.py
nagiosunity/commands/fc_port.py
nagiosunity/commands/io_module.py
nagiosunity/commands/lcc.py
nagiosunity/commands/lun.py
nagiosunity/commands/memory_module.py
nagiosunity/commands/pool.py
nagiosunity/commands/power_supply.py
nagiosunity/commands/sas_port.py
nagiosunity/commands/sp.py
nagiosunity/commands/ssc.py
nagiosunity/commands/ssd.py
nagiosunity/commands/system.py
nagiosunity/lib/__init__.py
nagiosunity/lib/unity.py
nagiosunity/lib/utils.py
nagiosunity/tests/__init__.py
nagiosunity/tests/utils.py
nagiosunity/tests/cli/__init__.py
nagiosunity/tests/cli/test_opt.py
nagiosunity/tests/commands/__init__.py
nagiosunity/tests/commands/test_all_commands.py
nagiosunity/tests/lib/__init__.py
nagiosunity/tests/lib/fake.py
nagiosunity/tests/lib/test_utils.py
