Metadata-Version: 2.0
Name: nagios-unity
Version: 0.1.2
Summary: Unity plugin for Nagios.
Home-page: http://github.com/thecodeteam/nagios-unity
Author: Peter Wang
Author-email: peter.wang13@dell.com
License: Apache Software License
Platform: all
Classifier: Development Status :: 4 - Beta
Classifier: Operating System :: OS Independent
Classifier: Intended Audience :: Developers
Classifier: License :: OSI Approved :: Apache Software License
Classifier: Programming Language :: Python
Classifier: Programming Language :: Python :: Implementation
Classifier: Programming Language :: Python :: 2
Classifier: Programming Language :: Python :: 2.7
Classifier: Programming Language :: Python :: 3
Classifier: Programming Language :: Python :: 3.4
Classifier: Programming Language :: Python :: 3.5
Classifier: Programming Language :: Python :: 3.6
Classifier: Topic :: Software Development :: Libraries
Requires-Dist: bitmath (>=1.3.0)
Requires-Dist: docopt (>=0.6.2)
Requires-Dist: requests
Requires-Dist: storops (>=0.5.0)
Requires-Dist: urllib3 (>=1.21.1)
